trait/__init__.py
trait/util.py
trait-0.0.2.dist-info/LICENSE
trait-0.0.2.dist-info/METADATA
trait-0.0.2.dist-info/WHEEL
trait-0.0.2.dist-info/top_level.txt
trait-0.0.2.dist-info/RECORD
