Metadata-Version: 2.1
Name: trait
Version: 0.0.2
Summary: ML featurizer and transformer tools
Home-page: https://github.com/otosense/trait
Author: OtoSense
License: apache-2.0
Platform: any
License-File: LICENSE
Requires-Dist: numpy
Requires-Dist: scikit-learn
